scp2/__init__.py
scp2/core.py
scp2-0.0.1.dist-info/entry_points.txt
scp2-0.0.1.dist-info/LICENSE
scp2-0.0.1.dist-info/WHEEL
scp2-0.0.1.dist-info/METADATA
scp2-0.0.1.dist-info/RECORD
